tetraux.cpython-39-x86_64-linux-gnu.so
tetraux-0.3.11.dist-info/METADATA
tetraux-0.3.11.dist-info/RECORD
tetraux-0.3.11.dist-info/top_level.txt
tetraux-0.3.11.dist-info/WHEEL
