Metadata-Version: 2.1
Name: tetraux
Version: 0.3.11
Summary: tetraux contains some auxiliary function and class used by tetragono.
Home-page: https://github.com/USTC-TNS/TAT/tree/TAT/tetraux
Author: Hao Zhang
Author-email: zh970205@mail.ustc.edu.cn
License: GPLv3
